alcokit/__init__.py
alcokit/algos.py
alcokit/score.py
alcokit/sources.py
alcokit/toolkit.py
alcokit/util.py
alcokit/extract/__init__.py
alcokit/extract/categories.py
alcokit/extract/pitch.py
alcokit/extract/segmentation.py
alcokit/extract/similarity.py
alcokit/fft/__init__.py
alcokit/hdf/__init__.py
alcokit/hdf/api.py
alcokit/hdf/factory.py
alcokit/models/__init__.py
alcokit/models/arconv.py
alcokit/models/arm.py
alcokit/models/conv_network.py
alcokit/models/data.py
alcokit/models/losses.py
alcokit/models/modules.py
alcokit/models/seq2seq_lstm.py
alcokit/models/utils.py
alcokit/transform/__init__.py
alcokit/transform/durations.py
alcokit/transform/pitch.py
alcokit/transform/spectrum.py
alcokit/transform/time.py
tests/__init__.py
tests/test_data.py
tests/test_score.py
tests/test_source.py
alcokit-0.0.14.dist-info/LICENSE
alcokit-0.0.14.dist-info/METADATA
alcokit-0.0.14.dist-info/WHEEL
alcokit-0.0.14.dist-info/top_level.txt
alcokit-0.0.14.dist-info/RECORD
